CHANGELOG.txt
LICENCE.txt
MANIFEST.in
README.txt
distribute_setup.py
setup.py
test.py
scratch/__init__.py
scratch.egg-info/PKG-INFO
scratch.egg-info/SOURCES.txt
scratch.egg-info/dependency_links.txt
scratch.egg-info/top_level.txt