Metadata-Version: 1.1
Name: scratch
Version: 0.0.1a
Summary: Interface Python with MIT Scratch
Home-page: https://code.google.com/p/py-scratch/
Author: Ben Croston
Author-email: ben@croston.org
License: MIT
Keywords: Scratch
Platform: UNKNOWN
Classifier: Development Status :: 3 - Alpha
Classifier: Operating System :: OS Independent
Classifier: License :: OSI Approved :: MIT License
Classifier: Intended Audience :: Developers
Classifier: Programming Language :: Python :: 2.6
Classifier: Programming Language :: Python :: 2.7
Classifier: Programming Language :: Python :: 3
Classifier: Programming Language :: Other
Classifier: Topic :: Software Development
Classifier: Intended Audience :: Education
